CHANGES.txt
README.txt
ez_setup.py
setup.py
Products/__init__.py
Products.whoopass.egg-info/PKG-INFO
Products.whoopass.egg-info/SOURCES.txt
Products.whoopass.egg-info/dependency_links.txt
Products.whoopass.egg-info/namespace_packages.txt
Products.whoopass.egg-info/not-zip-safe
Products.whoopass.egg-info/requires.txt
Products.whoopass.egg-info/top_level.txt
Products/whoopass/__init__.py
Products/whoopass/plugin.py
Products/whoopass/tests/__init__.py
Products/whoopass/tests/test_plugin.py
Products/whoopass/www/addWhoPluginForm.pt