Metadata-Version: 1.0
Name: Products.whoopass
Version: 0.2
Summary: repoze.who-aware authentication plugin for PAS
Home-page: UNKNOWN
Author: Agendaless Consulting, Inc.
Author-email: mailto:tseaver@agendaless.com
License: ZPL
Platform: UNKNOWN
Classifier: Programming Language :: Python
